{
    "title": "நித்தம் உற்றுனை",
    "santham": [
        "தத்தனத் தனனதத்த - தனதான"
    ],
    "lines": [
        "நித்தமுற் றுனைநினைத்து - மிகநாடி",
        "நிட்டைபெற் றியல்கருத்தர் - துணையாக",
        "நத்தியு தமதவத்தி - னெறியாலே",
        "லக்யலக் கணநிருத்த - மருள்வாயே",
        "வெற்றிவிக் ரமவரக்கர் - கிளைமாள",
        "விட்டநத் துகரனுக்கு - மருகோனே",
        "குற்றமற் றவருளத்தி - லுறைவோனே",
        "குக்குடக் கொடிதரித்த - பெருமாளே"
    ],
    "porul": null,
    "explanation": null,
    "music": null,
    "thalam": "பொதுப்பாடல்கள்"
}